hydronet/__init__.py
hydronet/wmm.py
hydronetapi-0.0.6.dist-info/METADATA
hydronetapi-0.0.6.dist-info/WHEEL
hydronetapi-0.0.6.dist-info/top_level.txt
hydronetapi-0.0.6.dist-info/RECORD
