Metadata-Version: 2.1
Name: hydronetapi
Version: 0.0.6
Summary: Hydronet WMM API
Author-email: Deniz Unal <deniz@bionetsonar.com>
Project-URL: Homepage, https://www.hydronet.tech/
Classifier: Programming Language :: Python :: 3
Classifier: License :: OSI Approved :: MIT License
Classifier: Operating System :: OS Independent
Requires-Python: >=3.8
